gt_push_sdk/BatchImpl.py
gt_push_sdk/GtConfig.py
gt_push_sdk/RequestException.py
gt_push_sdk/__init__.py
gt_push_sdk/alias_demo.py
gt_push_sdk/demo.py
gt_push_sdk/igt_push.py
gt_push_sdk/google/__init__.py
gt_push_sdk/google/protobuf/__init__.py
gt_push_sdk/google/protobuf/any_pb2.py
gt_push_sdk/google/protobuf/any_test_pb2.py
gt_push_sdk/google/protobuf/api_pb2.py
gt_push_sdk/google/protobuf/descriptor.py
gt_push_sdk/google/protobuf/descriptor_database.py
gt_push_sdk/google/protobuf/descriptor_pb2.py
gt_push_sdk/google/protobuf/descriptor_pool.py
gt_push_sdk/google/protobuf/duration_pb2.py
gt_push_sdk/google/protobuf/empty_pb2.py
gt_push_sdk/google/protobuf/field_mask_pb2.py
gt_push_sdk/google/protobuf/json_format.py
gt_push_sdk/google/protobuf/map_proto2_unittest_pb2.py
gt_push_sdk/google/protobuf/map_unittest_pb2.py
gt_push_sdk/google/protobuf/message.py
gt_push_sdk/google/protobuf/message_factory.py
gt_push_sdk/google/protobuf/proto_builder.py
gt_push_sdk/google/protobuf/reflection.py
gt_push_sdk/google/protobuf/service.py
gt_push_sdk/google/protobuf/service_reflection.py
gt_push_sdk/google/protobuf/source_context_pb2.py
gt_push_sdk/google/protobuf/struct_pb2.py
gt_push_sdk/google/protobuf/symbol_database.py
gt_push_sdk/google/protobuf/test_messages_proto2_pb2.py
gt_push_sdk/google/protobuf/test_messages_proto3_pb2.py
gt_push_sdk/google/protobuf/text_encoding.py
gt_push_sdk/google/protobuf/text_format.py
gt_push_sdk/google/protobuf/timestamp_pb2.py
gt_push_sdk/google/protobuf/type_pb2.py
gt_push_sdk/google/protobuf/unittest_arena_pb2.py
gt_push_sdk/google/protobuf/unittest_custom_options_pb2.py
gt_push_sdk/google/protobuf/unittest_import_pb2.py
gt_push_sdk/google/protobuf/unittest_import_public_pb2.py
gt_push_sdk/google/protobuf/unittest_mset_pb2.py
gt_push_sdk/google/protobuf/unittest_mset_wire_format_pb2.py
gt_push_sdk/google/protobuf/unittest_no_arena_import_pb2.py
gt_push_sdk/google/protobuf/unittest_no_arena_pb2.py
gt_push_sdk-4.0.3.2.dist-info/METADATA
gt_push_sdk-4.0.3.2.dist-info/WHEEL
gt_push_sdk-4.0.3.2.dist-info/top_level.txt
gt_push_sdk-4.0.3.2.dist-info/RECORD
