Metadata-Version: 2.1
Name: gt-push-sdk
Version: 4.0.3.2
Summary: Getui's officially supported Python3 client library
Home-page: http://docs.getui.com/getui/server/python3/start/
Author: GeTui
Author-email: support@getui.com
License: MIT License
Keywords: GeTui,GTPush API,Android Push,iOS Push
Platform: any
Classifier: Programming Language :: Python :: 3
Classifier: License :: OSI Approved :: MIT License
Classifier: Operating System :: OS Independent
